tc_aws_video/__init__.py
tc_aws_video/aws/__init__.py
tc_aws_video/aws/bucket.py
tc_aws_video/loaders/__init__.py
tc_aws_video/loaders/s3_video_loader.py
tests/__init__.py
tests/test_s3_video_loader.py
tests/fixtures/__init__.py
tests/fixtures/storage_fixture.py
tc_aws_video-2.0.2.dist-info/LICENSE
tc_aws_video-2.0.2.dist-info/METADATA
tc_aws_video-2.0.2.dist-info/WHEEL
tc_aws_video-2.0.2.dist-info/top_level.txt
tc_aws_video-2.0.2.dist-info/RECORD
