Metadata-Version: 2.1
Name: tc-aws-video
Version: 2.0.2
Summary: A customer loader for getting the video first frame from s3 compatible storage
Home-page: https://github.com/ethenoscar2011/tc-aws-video
Author: Ethenoscar
Author-email: ethenoscar2011@gmail.com
Classifier: Development Status :: 5 - Production/Stable
Classifier: Intended Audience :: Developers
Classifier: License :: OSI Approved :: MIT License
Classifier: Operating System :: OS Independent
Classifier: Topic :: Software Development :: Libraries :: Python Modules
Classifier: Topic :: Internet
Classifier: Programming Language :: Python :: 3
Classifier: Programming Language :: Python :: 3.6
Classifier: Programming Language :: Python :: 3.7
Classifier: Programming Language :: Python :: 3.8
License-File: LICENSE
Requires-Dist: thumbor >=7.0.0
Requires-Dist: botocore
Requires-Dist: subprocess32
Requires-Dist: tc-aws >=7.0.1
Requires-Dist: pycurl
